spotifynews/__init__.py
spotifynews/update.py
spotifynews/database/__init__.py
spotifynews/database/sqlite3db.py
spotifynews/spotify/__init__.py
spotifynews/spotify/client.py
tests/__init__.py
tests/test_client.py
tests/test_sqlite3db.py
tests/test_update.py
spotifynews-0.1.4.dist-info/LICENSE.md
spotifynews-0.1.4.dist-info/METADATA
spotifynews-0.1.4.dist-info/WHEEL
spotifynews-0.1.4.dist-info/top_level.txt
spotifynews-0.1.4.dist-info/RECORD
