Metadata-Version: 2.1
Name: spotifynews
Version: 0.1.4
Summary: Spotify news
Home-page: https://github.com/mpzaborski/spotifynews
Author: Mateusz Zaborski
Author-email: mpzaborski@gmail.com
License: UNKNOWN
Platform: UNKNOWN
Classifier: Programming Language :: Python :: 3
Classifier: License :: OSI Approved :: BSD License
Classifier: Operating System :: OS Independent
Requires-Python: >=3.7
Requires-Dist: atomicwrites (>=1.4.0)
Requires-Dist: attrs (>=20.3.0)
Requires-Dist: certifi (>=2020.12.0chardet>=4.0.0)
Requires-Dist: colorama (>=0.4.0idna>=2.10)
Requires-Dist: iniconfig (>=1.1.0)
Requires-Dist: packaging (>=20.9)
Requires-Dist: pluggy (>=0.13.0)
Requires-Dist: py (>=1.10.0)
Requires-Dist: pyparsing (>=2.4.7)
Requires-Dist: requests (>=2.25.0)
Requires-Dist: six (>=1.15.0)
Requires-Dist: spotipy (>=2.17.1)
Requires-Dist: toml (>=0.10.0)
Requires-Dist: urllib3 (>=1.26.0)
